rustico-0.1.7.dist-info/METADATA
rustico-0.1.7.dist-info/WHEEL
rustico-0.1.7.dist-info/entry_points.txt
rustico-0.1.7.dist-info/licenses/LICENSE.md
rustico/__init__.py
rustico/py.typed
rustico/rustico.egg-info/PKG-INFO
rustico/rustico.egg-info/SOURCES.txt
rustico/rustico.egg-info/dependency_links.txt
rustico/rustico.egg-info/top_level.txt
rustico/rustico.py
rustico-0.1.7.dist-info/RECORD
