Metadata-Version: 2.1
Name: rustico
Version: 0.1.3
Summary: A Rust-inspired, ergonomic Result type for Python with first-class async support, pattern matching, and a clean API.
Author-email: Simon Waiblinger <16225108+simwai@users.noreply.github.com>
License: MIT
Project-URL: Homepage, https://github.com/simwai/rustico
Project-URL: Documentation, https://github.com/simwai/rustico#readme
Project-URL: Source, https://github.com/simwai/rustico
Project-URL: Tracker, https://github.com/simwai/rustico/issues
Keywords: result,rust,error-handling,async,pattern-matching,monad,decorator,type-safety,python,functional-programming
Classifier: Programming Language :: Python :: 3
Classifier: Programming Language :: Python :: 3.8
Classifier: Programming Language :: Python :: 3.9
Classifier: Programming Language :: Python :: 3.10
Classifier: Programming Language :: Python :: 3.11
Classifier: Programming Language :: Python :: 3.12
Classifier: License :: OSI Approved :: MIT License
Classifier: Operating System :: OS Independent
Classifier: Development Status :: 4 - Beta
Classifier: Intended Audience :: Developers
Classifier: Topic :: Software Development :: Libraries :: Python Modules
Classifier: Typing :: Typed
Requires-Python: >=3.8
License-File: LICENSE.md
